asimtote/__init__.py
asimtote/__main__.py
asimtote/config.py
asimtote/diff.py
asimtote/misc.py
asimtote/ios/__init__.py
asimtote/ios/config.py
asimtote/ios/diff.py
asimtote/ios/utils.py
asimtote/ios/commands/__init__.py
asimtote/ios/commands/interface.py
asimtote/ios/commands/lists.py
asimtote/ios/commands/other.py
asimtote/ios/commands/router/__init__.py
asimtote/ios/commands/router/bgp.py
asimtote/ios/commands/router/msdp.py
asimtote/ios/commands/router/ospf.py
asimtote/ios/commands/router/rtmap.py
asimtote/ios/commands/router/static.py
asimtote/ios/converters/__init__.py
asimtote/ios/converters/interface.py
asimtote/ios/converters/lists.py
asimtote/ios/converters/other.py
asimtote/ios/converters/router/__init__.py
asimtote/ios/converters/router/bgp.py
asimtote/ios/converters/router/msdp.py
asimtote/ios/converters/router/ospf.py
asimtote/ios/converters/router/rtmap.py
asimtote/ios/converters/router/static.py
asimtote-0.16.17.dist-info/licenses/LICENSE
asimtote-0.16.17.dist-info/METADATA
asimtote-0.16.17.dist-info/WHEEL
asimtote-0.16.17.dist-info/top_level.txt
asimtote-0.16.17.dist-info/RECORD
