Metadata-Version: 2.4
Name: asimtote
Version: 0.16.17
Summary: Compare network device configuration files using contextual structures
Home-page: https://gitlab.developers.cam.ac.uk/uis/netsys/udn/asimtote
Author: Robert Franklin
Author-email: rcf34@cam.ac.uk
Classifier: Programming Language :: Python :: 3
Classifier: License :: OSI Approved :: MIT License
Classifier: Operating System :: OS Independent
License-File: LICENSE
Requires-Dist: deepops>=1.8
Requires-Dist: netaddr
Dynamic: author
Dynamic: author-email
Dynamic: classifier
Dynamic: description
Dynamic: description-content-type
Dynamic: home-page
Dynamic: license-file
Dynamic: requires-dist
Dynamic: summary
